LICENSE.txt
MANIFEST.in
README.md
setup.cfg
setup.py
pycnf/__init__.py
pycnf/configtype.py
pycnf/pycnf.py
pycnf/read.py
pycnf/utils.py
pycnf/write.py
pycnf.egg-info/PKG-INFO
pycnf.egg-info/SOURCES.txt
pycnf.egg-info/dependency_links.txt
pycnf.egg-info/entry_points.txt
pycnf.egg-info/requires.txt
pycnf.egg-info/top_level.txt
tests/config.error.ini
tests/config.error.json
tests/config.error.toml
tests/config.error.yaml
tests/config.ini
tests/config.json
tests/config.other.yaml
tests/config.toml
tests/config.yaml
tests/tests.py