Metadata-Version: 1.1
Name: pycnf
Version: 0.0.7
Summary: Implements the JSON, INI, YAML and TOML parser for Python setting and writing of configuration file.
Home-page: https://github.com/Miachol/pycnf
Author: Li Jianfeng
Author-email: lee_jianfeng@sjtu.edu.cn
License: MIT
Keywords: configuration setuptools development
Platform: UNKNOWN
Classifier: Development Status :: 3 - Alpha
Classifier: Intended Audience :: Developers
Classifier: Topic :: Software Development :: Build Tools
Classifier: License :: OSI Approved :: MIT License
Classifier: Programming Language :: Python :: 2
Classifier: Programming Language :: Python :: 2.7
Classifier: Programming Language :: Python :: 3
Classifier: Programming Language :: Python :: 3.3
Classifier: Programming Language :: Python :: 3.4
Classifier: Programming Language :: Python :: 3.5
